verilog/ALU/ALU.v
module ALU (
    input [0:31] A,B,
    input [0:2] Alucontrol,
    output reg [0:31] result,
    output reg Zero
);

always @(*) begin
    case (Alucontrol)
        3'b000: result = A+B ;   //  add
        3'b001: result = A-B ;   // subtract
        3'b010: result = A & B;  // and
        3'b011: result = A | B;  // or
        3'b101: result = A << B;    //slt
        default: result = 0;
    endcase
    if (result == 0)
        Zero = 1;
    else
        Zero = 0;
end
    
endmodule

ALU_tb.v
module ALU_tb(
);
reg [0:31] A,B;
reg [0:2] Alucontrol;
wire [0:31] result;
wire Zero;

ALU DUT(.A(A),.B(B),.Alucontrol(Alucontrol),.result(result),.Zero(Zero));

initial begin
    repeat(80)
    begin 
        A = $random %100;
        B = $random %100;
        Alucontrol = $random %6; // 4 NO DEFINIFO RESULT = 0
        #10;
end 
end

wire [63:0] timestamp;
assign timestamp = $time;

initial
begin
    $monitor("%4t | %d | %d | %d | %d | %d | \n ", timestamp, A, B, Alucontrol, result, Zero);
end

initial begin
    $dumpfile("ALU_TB.vcd");
    $dumpvars(0, ALU_tb);
end
endmodule

ALU_TB.vcd
$date
	Thu May 14 08:21:04 2026
$end
$version
	Icarus Verilog
$end
$timescale
	1s
$end
$scope module ALU_tb $end
$var wire 64 ! timestamp [63:0] $end
$var wire 32 " result [0:31] $end
$var wire 1 # Zero $end
$var reg 32 $ A [0:31] $end
$var reg 3 % Alucontrol [0:2] $end
$var reg 32 & B [0:31] $end
$scope module DUT $end
$var wire 32 ' A [0:31] $end
$var wire 3 ( Alucontrol [0:2] $end
$var wire 32 ) B [0:31] $end
$var reg 1 # Zero $end
$var reg 32 * result [0:31] $end
$upscope $end
$upscope $end
$enddefinitions $end
$comment Show the parameter values. $end
$dumpall
$end
#0
$dumpvars
b0 *
b11111111111111111111111110011101 )
b101 (
b110000 '
b11111111111111111111111110011101 &
b101 %
b110000 $
1#
b0 "
bz !
$end
#10
b111001 &
b111001 )
b11111111111111111111111111110111 $
b11111111111111111111111111110111 '
#20
0#
b11111111111111111111111111111011 "
b11111111111111111111111111111011 *
b11 %
b11 (
b11111111111111111111111111110010 &
b11111111111111111111111111110010 )
b11111111111111111111111110111001 $
b11111111111111111111111110111001 '
#30
b11101000000000000000000 "
b11101000000000000000000 *
b101 %
b101 (
b10010 &
b10010 )
b11101 $
b11101 '
#40
b10001 "
b10001 *
b1 %
b1 (
b1100 &
b1100 )
#50
1#
b0 "
b0 *
b100 %
b100 (
b11111111111111111111111110011101 &
b11111111111111111111111110011101 )
b11111111111111111111111110111010 $
b11111111111111111111111110111010 '
#60
b110 %
b110 (
b11111111111111111111111111010111 &
b11111111111111111111111111010111 )
b1010101 $
b1010101 '
#70
b100 %
b100 (
b1010110 &
b1010110 )
b100111 $
b100111 '
#80
0#
b11111111111111111111111111000100 "
b11111111111111111111111111000100 *
b10 %
b10 (
b11111111111111111111111111010101 &
b11111111111111111111111111010101 )
b11111111111111111111111111100100 $
b11111111111111111111111111100100 '
#90
1#
b0 "
b0 *
b101 %
b101 (
b11111111111111111111111110111101 &
b11111111111111111111111110111101 )
b11111111111111111111111111111101 $
b11111111111111111111111111111101 '
#100
b110 %
b110 (
b1011010 &
b1011010 )
b11111111111111111111111110110111 $
b11111111111111111111111110110111 '
#110
b111 %
b111 (
b1110 &
b1110 )
b100100 $
b100100 '
#120
b101 %
b101 (
b11111111111111111111111110111111 &
b11111111111111111111111110111111 )
b11111111111111111111111110110110 $
b11111111111111111111111110110110 '
#130
b110111 &
b110111 )
b11111111111111111111111111110011 $
b11111111111111111111111111110011 '
#140
0#
b11111111111111111111111111110110 "
b11111111111111111111111111110110 *
b11 %
b11 (
b11111111111111111111111111110010 &
b11111111111111111111111111110010 )
b11111111111111111111111111000110 $
b11111111111111111111111111000110 '
#150
b101111 "
b101111 *
b10 %
b10 (
b101111 &
b101111 )
b11111111111111111111111111101111 $
b11111111111111111111111111101111 '
#160
b11111111111111111111111110100000 "
b11111111111111111111111110100000 *
b11111111111111111111111110101000 &
b11111111111111111111111110101000 )
b11111111111111111111111111100010 $
b11111111111111111111111111100010 '
#170
1#
b0 "
b0 *
b100 %
b100 (
b111001 &
b111001 )
b11110 $
b11110 '
#180
0#
b1010111 "
b1010111 *
b1 %
b1 (
b11111111111111111111111111010001 &
b11111111111111111111111111010001 )
b101000 $
b101000 '
#190
1#
b0 "
b0 *
b100 %
b100 (
b11010 &
b11010 )
b1000010 $
b1000010 '
#200
b111 %
b111 (
b1011110 &
b1011110 )
b11111111111111111111111111100000 $
b11111111111111111111111111100000 '
#210
0#
b11111111111111111111111110011000 "
b11111111111111111111111110011000 *
b1 %
b1 (
b101001 &
b101001 )
b11111111111111111111111111000001 $
b11111111111111111111111111000001 '
#220
1#
b0 "
b0 *
b100 %
b100 (
b1011110 &
b1011110 )
b11111111111111111111111111111011 $
b11111111111111111111111111111011 '
#230
0#
b11111111111111111111111111001100 "
b11111111111111111111111111001100 *
b1 %
b1 (
b110101 &
b110101 )
b1 $
b1 '
#240
b11111111111111111111111111110010 "
b11111111111111111111111111110010 *
b110000 &
b110000 )
b100010 $
b100010 '
#250
b11011100000000000000000000 "
b11011100000000000000000000 *
b101 %
b101 (
b10100 &
b10100 )
b110111 $
b110111 '
#260
b11111111111111111111111111101011 "
b11111111111111111111111111101011 *
b11 %
b11 (
b11111111111111111111111111100000 &
b11111111111111111111111111100000 )
b11111111111111111111111111001011 $
b11111111111111111111111111001011 '
#270
1#
b0 "
b0 *
b100 %
b100 (
b11111111111111111111111111011101 &
b11111111111111111111111111011101 )
b1100001 $
b1100001 '
#280
0#
b11111111111111111111111111000101 "
b11111111111111111111111111000101 *
b10 %
b10 (
b11111111111111111111111111001101 &
b11111111111111111111111111001101 )
b11111111111111111111111111100111 $
b11111111111111111111111111100111 '
#290
b11111111111111111111111111101110 "
b11111111111111111111111111101110 *
b0 %
b0 (
b11111111111111111111111110101110 &
b11111111111111111111111110101110 )
b1000000 $
b1000000 '
#300
b11111111111111111111111111011000 "
b11111111111111111111111111011000 *
b11001 &
b11001 )
b11111111111111111111111110111111 $
b11111111111111111111111110111111 '
#310
1#
b0 "
b0 *
b101 %
b101 (
b101001 &
b101001 )
b11111111111111111111111111011110 $
b11111111111111111111111111011110 '
#320
0#
b111100 "
b111100 *
b1 %
b1 (
b11111111111111111111111111101011 &
b11111111111111111111111111101011 )
b100111 $
b100111 '
#330
1#
b0 "
b0 *
b101 %
b101 (
b101011 &
b101011 )
b11111111111111111111111111100000 $
b11111111111111111111111111100000 '
#340
0#
b11111111111111111111111111101001 "
b11111111111111111111111111101001 *
b0 %
b0 (
b1010 &
b1010 )
b11111111111111111111111111011111 $
b11111111111111111111111111011111 '
#350
1#
b0 "
b0 *
b100 %
b100 (
b11111111111111111111111111000010 &
b11111111111111111111111111000010 )
b11111111111111111111111111011010 $
b11111111111111111111111111011010 '
#360
0#
b11111111111111111111111110111010 "
b11111111111111111111111110111010 *
b11 %
b11 (
b11111111111111111111111110110010 &
b11111111111111111111111110110010 )
b11010 $
b11010 '
#370
b11111111111111111111111111111111 "
b11111111111111111111111111111111 *
b11111111111111111111111111101111 &
b11111111111111111111111111101111 )
b11111111111111111111111111111011 $
b11111111111111111111111111111011 '
#380
b11111111111111111111111111100111 "
b11111111111111111111111111100111 *
b1 %
b1 (
b10000 &
b10000 )
b11111111111111111111111111110111 $
b11111111111111111111111111110111 '
#390
1#
b0 "
b0 *
b100 %
b100 (
b11111111111111111111111110011110 &
b11111111111111111111111110011110 )
b11111111111111111111111111100111 $
b11111111111111111111111111100111 '
#400
0#
b11111111111111111111111110111110 "
b11111111111111111111111110111110 *
b0 %
b0 (
b11111111111111111111111110101001 &
b11111111111111111111111110101001 )
b10101 $
b10101 '
#410
b11111111111111111111111111111101 "
b11111111111111111111111111111101 *
b11 %
b11 (
b11111111111111111111111111111101 &
b11111111111111111111111111111101 )
b11111111111111111111111111100001 $
b11111111111111111111111111100001 '
#420
b1110001 "
b1110001 *
b0 %
b0 (
b111000 &
b111000 )
b111001 $
b111001 '
#430
b1011101 "
b1011101 *
b1001011 &
b1001011 )
b10010 $
b10010 '
#440
1#
b0 "
b0 *
b101 %
b101 (
b11111111111111111111111111001110 &
b11111111111111111111111111001110 )
b10000 $
b10000 '
#450
0#
b100101 "
b100101 *
b0 %
b0 (
b110010 &
b110010 )
b11111111111111111111111111110011 $
b11111111111111111111111111110011 '
#460
b11111111111111111111111110100110 "
b11111111111111111111111110100110 *
b10 %
b10 (
b11111111111111111111111110101110 &
b11111111111111111111111110101110 )
b11111111111111111111111111110111 $
b11111111111111111111111111110111 '
#470
b110101 "
b110101 *
b0 %
b0 (
b1000001 &
b1000001 )
b11111111111111111111111111110100 $
b11111111111111111111111111110100 '
#480
b110111 "
b110111 *
b110011 &
b110011 )
b100 $
b100 '
#490
1#
b0 "
b0 *
b111 %
b111 (
b11111111111111111111111111001001 $
b11111111111111111111111111001001 '
#500
b100 %
b100 (
b11111111111111111111111111010101 &
b11111111111111111111111111010101 )
b11101 $
b11101 '
#510
0#
b1011110 "
b1011110 *
b11 %
b11 (
b1010110 &
b1010110 )
b11110 $
b11110 '
#520
1#
b0 "
b0 *
b101 %
b101 (
b1011100 &
b1011100 )
b11111111111111111111111111110110 $
b11111111111111111111111111110110 '
#530
b100 %
b100 (
b11111111111111111111111111001100 &
b11111111111111111111111111001100 )
b1 $
b1 '
#540
0#
b11111111111111111111111111011101 "
b11111111111111111111111111011101 *
b11 %
b11 (
b11111111111111111111111111010101 &
b11111111111111111111111111010101 )
b1001100 $
b1001100 '
#550
b11111111111111111111111110101000 "
b11111111111111111111111110101000 *
b10 %
b10 (
b11111111111111111111111111101000 &
b11111111111111111111111111101000 )
b11111111111111111111111110101010 $
b11111111111111111111111110101010 '
#560
1#
b0 "
b0 *
b100 %
b100 (
b101001 &
b101001 )
b11111111111111111111111110111001 $
b11111111111111111111111110111001 '
#570
b111 %
b111 (
b11111111111111111111111110111110 &
b11111111111111111111111110111110 )
b1010010 $
b1010010 '
#580
b11111111111111111111111111111100 &
b11111111111111111111111111111100 )
b1001110 $
b1001110 '
#590
0#
b1000100 "
b1000100 *
b0 %
b0 (
b111010 &
b111010 )
b1010 $
b1010 '
#600
1#
b0 "
b0 *
b111 %
b111 (
b11111111111111111111111111010110 &
b11111111111111111111111111010110 )
b1 $
b1 '
#610
0#
b1110001 "
b1110001 *
b0 %
b0 (
b100010 &
b100010 )
b1001111 $
b1001111 '
#620
b11111111111111111111111111011110 "
b11111111111111111111111111011110 *
b11 %
b11 (
b11111111111111111111111111011110 &
b11111111111111111111111111011110 )
b1001110 $
b1001110 '
#630
b1101110 "
b1101110 *
b0 %
b0 (
b1000110 &
b1000110 )
b101000 $
b101000 '
#640
b11111111111111111111111111110111 "
b11111111111111111111111111110111 *
b11 %
b11 (
b11111111111111111111111111010111 &
b11111111111111111111111111010111 )
b110110 $
b110110 '
#650
1#
b0 "
b0 *
b111 %
b111 (
b11111111111111111111111110100110 &
b11111111111111111111111110100110 )
b10101 $
b10101 '
#660
0#
b11111111111111111111111111011100 "
b11111111111111111111111111011100 *
b0 %
b0 (
b11111111111111111111111110111101 &
b11111111111111111111111110111101 )
b11111 $
b11111 '
#670
b11111000000000000000000000000000 "
b11111000000000000000000000000000 *
b101 %
b101 (
b10101 &
b10101 )
b11111111111111111111111111000000 $
b11111111111111111111111111000000 '
#680
1#
b0 "
b0 *
b111 %
b111 (
b110101 &
b110101 )
b11111111111111111111111111110001 $
b11111111111111111111111111110001 '
#690
0#
b11111111111111111111111111111111 "
b11111111111111111111111111111111 *
b11 %
b11 (
b111111 &
b111111 )
b11111111111111111111111111000000 $
b11111111111111111111111111000000 '
#700
b11111111111111111111111110001110 "
b11111111111111111111111110001110 *
b0 %
b0 (
b11111111111111111111111110100010 &
b11111111111111111111111110100010 )
b11111111111111111111111111101100 $
b11111111111111111111111111101100 '
#710
1#
b0 "
b0 *
b111 %
b111 (
b1000101 &
b1000101 )
b11111111111111111111111110111100 $
b11111111111111111111111110111100 '
#720
b101 %
b101 (
b11111111111111111111111110100010 &
b11111111111111111111111110100010 )
b1010010 $
b1010010 '
#730
0#
b101110 "
b101110 *
b11 %
b11 (
b101010 &
b101010 )
b110 $
b110 '
#740
1#
b0 "
b0 *
b111 %
b111 (
b11111111111111111111111111011000 &
b11111111111111111111111111011000 )
b1110 $
b1110 '
#750
0#
b101110 "
b101110 *
b11 %
b11 (
b101010 &
b101010 )
b1100 $
b1100 '
#760
1#
b0 "
b0 *
b100 %
b100 (
b11111111111111111111111111011111 &
b11111111111111111111111111011111 )
b1000111 $
b1000111 '
#770
0#
b1110 "
b1110 *
b1 %
b1 (
b100000 &
b100000 )
b101110 $
b101110 '
#780
b111010 "
b111010 *
b11111111111111111111111111011100 &
b11111111111111111111111111011100 )
b10110 $
b10110 '
#790
1#
b0 "
b0 *
b100 %
b100 (
b1011110 &
b1011110 )
b11111111111111111111111111010110 $
b11111111111111111111111111010110 '
